{
  "type": "product",
  "currency": "EUR",
  "itemName": "Goliath Jelly Blox Set",
  "code": "6239903",
  "price": "8.99",
  "priceOriginal": "",
  "itemBgbcat": "2096 > 2132 > 2331 > 2731 > 3434 > 5921",
  "supplier": "GOLIATH B.V.",
  "inStock": "inStock",
  "onPromo": "1056415",
  "mmkId": "1056415",
  "productGroupId": "494883",
  "brandType": "A of B merk",
  "discount": "",
  "url": "/goliath-jelly-blox-set/p/6239903",
  "listName": "Lister",
  "brand": "Goliath",
  "mpOrigin": "Kruidvat",
  "mpShopId": "1",
  "isSponsored": "false",
  "categories": [
    {
      "id": 29536081,
      "name": "Speelgoed"
    },
    {
      "id": 30266026,
      "name": "Baby- en peuterspeelgoed"
    },
    {
      "id": 49281541,
      "name": "Interactief speelgoed"
    }
  ],
  "description": "",
  "image": "/medias/sys_master/prd-images/h75/h86/35104240697374/prd-front-6239903-1_600x600/prd-front-6239903-1-600x600.jpg"
}