{
  "type": "product",
  "currency": "EUR",
  "itemName": "LEGO Ninjago 71840 Rogue vs. Drix Racewagenduel",
  "code": "6346737",
  "price": "17.99",
  "priceOriginal": "",
  "itemBgbcat": "2141 > 2346 > 2747 > 3455 > 5921 > 6040",
  "supplier": "LEGO BENELUX BV (BNL)",
  "inStock": "inStock",
  "onPromo": "1056715",
  "mmkId": "1056715",
  "productGroupId": "500705",
  "brandType": "A of B merk",
  "discount": "",
  "url": "/lego-ninjago-71840-rogue-vs-drix-racewagenduel/p/6346737",
  "listName": "Lister",
  "brand": "LEGO Ninjago",
  "mpOrigin": "Kruidvat",
  "mpShopId": "1",
  "isSponsored": "false",
  "categories": [
    {
      "id": 29536081,
      "name": "Speelgoed"
    },
    {
      "id": 30266025,
      "name": "LEGO"
    },
    {
      "id": 30266812,
      "name": "LEGO Ninjago"
    }
  ],
  "description": "",
  "image": "/medias/sys_master/prd-images/h70/h23/34947736141854/prd-front-6346737-1_600x600/prd-front-6346737-1-600x600.jpg"
}