{
  "type": "product",
  "currency": "EUR",
  "itemName": "Alessandro Striplac UV Colour 159 Cheers! Nagellak",
  "code": "6368990",
  "price": "10.99",
  "priceOriginal": "",
  "itemBgbcat": "2002 > 6497 > 6496 > 6505 > 6506 > 6520",
  "supplier": "LEIJTENS IMPORT BV",
  "inStock": "inStock",
  "onPromo": "",
  "mmkId": "",
  "productGroupId": "",
  "brandType": "Exclusief merk",
  "discount": "",
  "url": "/alessandro-striplac-uv-colour-159-cheers-nagellak/p/6368990",
  "listName": "Lister",
  "brand": "Alessandro",
  "mpOrigin": "Kruidvat",
  "mpShopId": "1",
  "isSponsored": "false",
  "categories": [
    {
      "id": 29536077,
      "name": "Beauty"
    },
    {
      "id": 72475724,
      "name": "Nagels"
    },
    {
      "id": 30266584,
      "name": "Nagellak"
    }
  ],
  "description": "6,5ml"
}