{
  "type": "product",
  "currency": "EUR",
  "itemName": "Jumbo Knibbel Knabbel Knuisje",
  "code": "6319297",
  "price": "19.99",
  "priceOriginal": "",
  "itemBgbcat": "2181 > 5921 > 6018 > 6741 > 6740 > 6739",
  "supplier": "JUMBO NL BV",
  "inStock": "inStock",
  "onPromo": "1055979",
  "mmkId": "1055979",
  "productGroupId": "494124",
  "brandType": "A of B merk",
  "discount": "",
  "url": "/jumbo-knibbel-knabbel-knuisje/p/6319297",
  "listName": "Lister",
  "brand": "Jumbo",
  "mpOrigin": "Kruidvat",
  "mpShopId": "1",
  "isSponsored": "false",
  "categories": [
    {
      "id": 29536081,
      "name": "Speelgoed"
    },
    {
      "id": 30266027,
      "name": "Spellen"
    },
    {
      "id": 30266835,
      "name": "Bordspellen"
    }
  ],
  "description": ""
}