{
  "type": "product",
  "currency": "EUR",
  "itemName": "Revolution Peach Bliss Reloaded Blush",
  "code": "4989426",
  "price": "5.99",
  "priceOriginal": "",
  "itemBgbcat": "2002 > 2069 > 2210 > 2378 > 2819 > 5687",
  "supplier": "NORDIC BEAUTY COMPANY APS",
  "inStock": "inStock",
  "onPromo": "1005487",
  "mmkId": "1005487",
  "productGroupId": "",
  "brandType": "Exclusief merk",
  "discount": "",
  "url": "/revolution-peach-bliss-reloaded-blush/p/4989426",
  "listName": "Lister",
  "brand": "Revolution",
  "mpOrigin": "Kruidvat",
  "mpShopId": "1",
  "isSponsored": "false",
  "categories": [
    {
      "id": 29536077,
      "name": "Beauty"
    },
    {
      "id": 30265987,
      "name": "Make-up"
    },
    {
      "id": 30266590,
      "name": "Blush"
    }
  ],
  "description": "7,5g",
  "image": "/medias/sys_master/prd-images/hb6/hd6/34100528873502/prd-front-4989426-1_600x600/prd-front-4989426-1-600x600.jpg"
}