{
  "type": "product",
  "currency": "USD",
  "itemName": "Kruidvat Wratten Bevriezing",
  "code": "6059065",
  "price": "13.99",
  "priceOriginal": "",
  "itemBgbcat": "2006 > 2052 > 2175 > 6458 > 6457 > 6788",
  "supplier": "OTC MEDICAL BV",
  "inStock": "inStock",
  "onPromo": "1008193",
  "mmkId": "1008193",
  "productGroupId": "218105",
  "brandType": "Eigen merk",
  "discount": "",
  "url": "/kruidvat-wratten-bevriezing/p/6059065",
  "listName": "Lister",
  "brand": "Kruidvat",
  "mpOrigin": "Kruidvat",
  "mpShopId": "1",
  "isSponsored": "false",
  "categories": [
    {
      "id": 29536079,
      "name": "Gezondheid"
    },
    {
      "id": 48220663,
      "name": "Voetongemakken"
    },
    {
      "id": 101911637,
      "name": "Voetwratten"
    }
  ],
  "description": "Medisch hulpmiddel - 50ml, 12 behandelingen"
}