{
  "type": "product",
  "currency": "EUR",
  "itemName": "999 Games Kakkerlakkenpoker",
  "code": "6234478",
  "price": "9.99",
  "priceOriginal": "",
  "itemBgbcat": "2181 > 5162 > 5217 > 5406 > 5921 > 6018",
  "supplier": "999 GAMES",
  "inStock": "inStock",
  "onPromo": "1053749",
  "mmkId": "1053749",
  "productGroupId": "",
  "brandType": "A of B merk",
  "discount": "",
  "url": "/999-games-kakkerlakkenpoker/p/6234478",
  "listName": "Lister",
  "brand": "999 Games",
  "mpOrigin": "Kruidvat",
  "mpShopId": "1",
  "isSponsored": "false",
  "categories": [
    {
      "id": 29536081,
      "name": "Speelgoed"
    },
    {
      "id": 30266027,
      "name": "Spellen"
    },
    {
      "id": 49281411,
      "name": "Kaartspellen"
    }
  ],
  "description": "Nederlandstalig spel",
  "image": "/medias/sys_master/prd-images/h97/h77/32720435347486/prd-front-6234478-1_600x600/prd-front-6234478-1-600x600.jpg"
}