{
  "type": "product",
  "currency": "EUR",
  "itemName": "Tooth Fairy Tooth Crystal Kit",
  "code": "6174719",
  "price": "12.99",
  "priceOriginal": "",
  "itemBgbcat": "2002 > 2221 > 2492 > 3057 > 3905 > 6674",
  "supplier": "REBRO COSMETICS BV",
  "inStock": "inStock",
  "onPromo": "1053153",
  "mmkId": "1053153",
  "productGroupId": "478519",
  "brandType": "A of B merk",
  "discount": "",
  "url": "/tooth-fairy-tooth-crystal-kit/p/6174719",
  "listName": "Lister",
  "brand": "Tooth Fairy",
  "mpOrigin": "Kruidvat",
  "mpShopId": "1",
  "isSponsored": "false",
  "categories": [
    {
      "id": 29536082,
      "name": "Fashion"
    },
    {
      "id": 30266046,
      "name": "Accessoires"
    },
    {
      "id": 30266860,
      "name": "Sieraden en bijoux"
    }
  ],
  "description": "",
  "image": "/medias/sys_master/prd-images/hb6/h7d/32639269142558/prd-front-6174719-1_600x600/prd-front-6174719-1-600x600.jpg"
}