{
  "type": "product",
  "currency": "EUR",
  "itemName": "Kruidvat Repair Calendula Extract Bodylotion",
  "code": "2748502",
  "price": "3.29",
  "priceOriginal": "",
  "itemBgbcat": "2003 > 2059 > 2139 > 2342 > 3108 > 3485",
  "supplier": "ROYAL SANDERS (BNL)",
  "inStock": "inStock",
  "onPromo": "1052906",
  "mmkId": "1052906",
  "productGroupId": "471317",
  "brandType": "Eigen merk",
  "discount": "",
  "url": "/kruidvat-repair-calendula-extract-bodylotion/p/2748502",
  "listName": "Lister",
  "brand": "Kruidvat",
  "mpOrigin": "Kruidvat",
  "mpShopId": "1",
  "isSponsored": "false",
  "categories": [
    {
      "id": 29536078,
      "name": "Verzorging"
    },
    {
      "id": 30265995,
      "name": "Huidverzorging"
    },
    {
      "id": 30266637,
      "name": "Bodylotion"
    }
  ],
  "description": "400ml",
  "image": "/medias/sys_master/prd-images/h4c/h86/34356279312414/prd-front-2748502-1_600x600/prd-front-2748502-1-600x600.jpg"
}