{
  "type": "product",
  "currency": "EUR",
  "itemName": "Merci Finest Selection Luxe Geschenkdoos",
  "code": "23798",
  "price": "7.99",
  "priceOriginal": "8.99",
  "itemBgbcat": "2004 > 2094 > 2281 > 2366 > 2796 > 3537",
  "supplier": "STORCK BV",
  "inStock": "inStock",
  "onPromo": "1057164",
  "mmkId": "1057164",
  "productGroupId": "489131",
  "brandType": "A of B merk",
  "discount": "€ 1,00",
  "url": "/merci-finest-selection-luxe-geschenkdoos/p/23798",
  "listName": "Lister",
  "brand": "Merci",
  "mpOrigin": "Kruidvat",
  "mpShopId": "1",
  "isSponsored": "false",
  "categories": [
    {
      "id": 30266076,
      "name": "Eten en drinken"
    },
    {
      "id": 30266884,
      "name": "Snacks en snoep"
    },
    {
      "id": 30267024,
      "name": "Chocolade"
    },
    {
      "id": 107464837,
      "name": "Chocoladegeschenken"
    }
  ],
  "description": "400g",
  "image": "/medias/sys_master/prd-images/h33/h91/44747327832094/prd-front-23798-1_600x600/prd-front-23798-1-600x600.jpg"
}