{
  "type": "product",
  "currency": "EUR",
  "itemName": "Medela Ultra-Ademende Zoogkompressen",
  "code": "6069180",
  "price": "10.99",
  "priceOriginal": "",
  "itemBgbcat": "2001 > 2031 > 2218 > 2484 > 3050 > 3899",
  "supplier": "MEDELA BENELUX BV",
  "inStock": "outOfStock",
  "onPromo": "1057060",
  "mmkId": "1057060",
  "productGroupId": "510685",
  "brandType": "A of B merk",
  "discount": "",
  "url": "/medela-ultra-ademende-zoogkompressen/p/6069180",
  "listName": "Lister",
  "brand": "Medela",
  "mpOrigin": "Kruidvat",
  "mpShopId": "1",
  "isSponsored": "false",
  "categories": [
    {
      "id": 29536080,
      "name": "Baby"
    },
    {
      "id": 30266023,
      "name": "Zwangerschap en kraamtijd"
    },
    {
      "id": 30266806,
      "name": "Zoogkompressen"
    }
  ],
  "description": "60 stuks",
  "image": "/medias/sys_master/prd-images/h11/h99/30948259266590/prd-front-6069180-1_600x600/prd-front-6069180-1-600x600.jpg"
}