{
  "type": "product",
  "currency": "EUR",
  "itemName": "Hismile Teeth Brightening PAP+ Pen",
  "code": "6289841",
  "price": "24.99",
  "priceOriginal": "",
  "itemBgbcat": "2003 > 2075 > 2223 > 2639 > 3323 > 6336",
  "supplier": "HISMILE PTY LTD.",
  "inStock": "inStock",
  "onPromo": "1058759",
  "mmkId": "1058759",
  "productGroupId": "480361",
  "brandType": "A of B merk",
  "discount": "",
  "url": "/hismile-teeth-brightening-pap-pen/p/6289841",
  "listName": "Lister",
  "brand": "HISMILE",
  "mpOrigin": "Kruidvat",
  "mpShopId": "1",
  "isSponsored": "false",
  "categories": [
    {
      "id": 29536078,
      "name": "Verzorging"
    },
    {
      "id": 30266001,
      "name": "Mondverzorging"
    },
    {
      "id": 49742365,
      "name": "Whitening producten"
    }
  ],
  "description": "3ml",
  "image": "/medias/sys_master/prd-images/hc2/hbc/34147170615326/prd-front-6289841-1_600x600/prd-front-6289841-1-600x600.jpg"
}