{
  "type": "product",
  "currency": "EUR",
  "itemName": "SKIN1004 Madagascar Centella Toning Toner",
  "code": "6200535",
  "price": "8.17",
  "priceOriginal": "10.9",
  "itemBgbcat": "2002 > 2089 > 2256 > 2804 > 4226 > 6702",
  "supplier": "ORIEN TRADE OU",
  "inStock": "inStock",
  "onPromo": "1058266",
  "mmkId": "1058266",
  "productGroupId": "484751",
  "brandType": "A of B merk",
  "discount": "€ 2,73",
  "url": "/skin1004-madagascar-centella-toning-toner/p/6200535",
  "listName": "Lister",
  "brand": "SKIN1004",
  "mpOrigin": "Kruidvat",
  "mpShopId": "1",
  "isSponsored": "false",
  "categories": [
    {
      "id": 29536077,
      "name": "Beauty"
    },
    {
      "id": 30265991,
      "name": "Skincare"
    },
    {
      "id": 30266608,
      "name": "Gezichtsreiniging"
    },
    {
      "id": 73443559,
      "name": "Toner"
    }
  ],
  "description": "30ml - Alle huidtypen"
}