{
  "type": "product",
  "currency": "EUR",
  "itemName": "True Spirit Geruite Sjaal",
  "code": "6253805",
  "price": "6.99",
  "priceOriginal": "",
  "itemBgbcat": "2048 > 2225 > 4869 > 5069 > 5071 > 5096",
  "supplier": "AS WATSON (TRAD.HK LIM)",
  "inStock": "inStock",
  "onPromo": "1058624",
  "mmkId": "1058624",
  "productGroupId": "513373",
  "brandType": "Eigen merk",
  "discount": "",
  "url": "/true-spirit-geruite-sjaal/p/6253805",
  "listName": "Lister",
  "brand": "Truespirit",
  "mpOrigin": "Kruidvat",
  "mpShopId": "1",
  "isSponsored": "false",
  "categories": [
    {
      "id": 29536082,
      "name": "Fashion"
    },
    {
      "id": 30266046,
      "name": "Accessoires"
    },
    {
      "id": 30266866,
      "name": "Winteraccessoires"
    }
  ],
  "description": "bruin, 200cm x 65cm"
}