{
  "type": "product",
  "currency": "USD",
  "itemName": "NYX Professional Makeup Powder Louder Taupe Brow Pencil",
  "code": "6129912",
  "price": "8.95",
  "priceOriginal": "",
  "itemBgbcat": "2002 > 2069 > 2210 > 2422 > 6131 > 6132",
  "supplier": "NYX PROFESSIONAL MAKE-UP",
  "inStock": "inStock",
  "onPromo": "1005487",
  "mmkId": "1005487",
  "productGroupId": "",
  "brandType": "A of B merk",
  "discount": "",
  "url": "/nyx-professional-makeup-powder-louder-taupe-brow-pencil/p/6129912",
  "listName": "Lister",
  "brand": "NYX Professional Makeup",
  "mpOrigin": "Kruidvat",
  "mpShopId": "1",
  "isSponsored": "false",
  "categories": [
    {
      "id": 29536077,
      "name": "Beauty"
    },
    {
      "id": 30265987,
      "name": "Make-up"
    },
    {
      "id": 30266592,
      "name": "Wenkbrauw make-up"
    },
    {
      "id": 30266908,
      "name": "Wenkbrauwpotlood"
    }
  ],
  "description": ""
}