{
  "type": "product",
  "currency": "EUR",
  "itemName": "True Spirit Damestop met Panterprint",
  "code": "6267014",
  "price": "6.99",
  "priceOriginal": "",
  "itemBgbcat": "2640 > 3325 > 4829 > 5813 > 5928 > 6038",
  "supplier": "FULLY FASHION",
  "inStock": "inStock",
  "onPromo": "1052872",
  "mmkId": "1052872",
  "productGroupId": "457485",
  "brandType": "Eigen merk",
  "discount": "",
  "url": "/true-spirit-damestop-met-panterprint/p/6267014",
  "listName": "Lister",
  "brand": "Truespirit",
  "mpOrigin": "Kruidvat",
  "mpShopId": "1",
  "isSponsored": "false",
  "categories": [
    {
      "id": 29536082,
      "name": "Fashion"
    },
    {
      "id": 30266039,
      "name": "Dames"
    },
    {
      "id": 30266841,
      "name": "Dameskleding"
    }
  ],
  "description": "mt S-M",
  "image": "/medias/sys_master/prd-images/h6b/h70/33739445927966/prd-front-6267014-1_600x600/prd-front-6267014-1-600x600.jpg"
}