{
  "type": "product",
  "currency": "EUR",
  "itemName": "Kruidvat Menthol Gel",
  "code": "2449042",
  "price": "3.39",
  "priceOriginal": "",
  "itemBgbcat": "2003 > 2059 > 2139 > 2342 > 3314 > 4217",
  "supplier": "GALVASTORE BV",
  "inStock": "inStock",
  "onPromo": "1028975",
  "mmkId": "1028975",
  "productGroupId": "362258",
  "brandType": "Eigen merk",
  "discount": "",
  "url": "/kruidvat-menthol-gel/p/2449042",
  "listName": "Lister",
  "brand": "Kruidvat",
  "mpOrigin": "Kruidvat",
  "mpShopId": "1",
  "isSponsored": "false",
  "categories": [
    {
      "id": 29536079,
      "name": "Gezondheid"
    },
    {
      "id": 30266006,
      "name": "Zelfzorg"
    },
    {
      "id": 51214305,
      "name": "Speciale huidverzorging"
    },
    {
      "id": 51216456,
      "name": "Verkoelende zalf"
    }
  ],
  "description": "100ml",
  "image": "/medias/sys_master/prd-images/h2b/h82/27400018427934/prd-front-2449042-1_600x600/prd-front-2449042-1-600x600.jpg"
}