{
  "type": "product",
  "currency": "EUR",
  "itemName": "Lucovitaal Cookie Caramel Smaakdruppels",
  "code": "6377390",
  "price": "3.99",
  "priceOriginal": "",
  "itemBgbcat": "2006 > 2261 > 2607 > 6391 > 6392 > 6397",
  "supplier": "PK BENELUX BV",
  "inStock": "inStock",
  "onPromo": "1061732",
  "mmkId": "1061732",
  "productGroupId": "511231",
  "brandType": "A of B merk",
  "discount": "",
  "url": "/lucovitaal-cookie-caramel-smaakdruppels/p/6377390",
  "listName": "Lister",
  "brand": "Lucovitaal",
  "mpOrigin": "Kruidvat",
  "mpShopId": "1",
  "isSponsored": "false",
  "categories": [
    {
      "id": 30266076,
      "name": "Eten en drinken"
    },
    {
      "id": 30266888,
      "name": "Zoetstoffen"
    }
  ],
  "description": "20ml",
  "image": "/medias/sys_master/prd-images/hfb/h90/44240641163294/prd-front-6377390-1_600x600/prd-front-6377390-1-600x600.jpg"
}