{
  "type": "product",
  "currency": "EUR",
  "itemName": "Kruidvat Moments Jasmine & Tucuma Butter Bodylotion",
  "code": "6283037",
  "price": "4.99",
  "priceOriginal": "",
  "itemBgbcat": "2003 > 2059 > 2139 > 2342 > 3036 > 3484",
  "supplier": "MAXIM MARKENPRODUKTE",
  "inStock": "outOfStock",
  "onPromo": "",
  "mmkId": "",
  "productGroupId": "",
  "brandType": "Eigen merk",
  "discount": "",
  "url": "/kruidvat-moments-jasmine-tucuma-butter-bodylotion/p/6283037",
  "listName": "Lister",
  "brand": "Kruidvat Moments",
  "mpOrigin": "Kruidvat",
  "mpShopId": "1",
  "isSponsored": "false",
  "categories": [
    {
      "id": 29536078,
      "name": "Verzorging"
    },
    {
      "id": 30265995,
      "name": "Huidverzorging"
    },
    {
      "id": 30266637,
      "name": "Bodylotion"
    }
  ],
  "description": "300ml",
  "image": "/medias/sys_master/prd-images/hcc/h1b/33850952744990/prd-front-6283037-1_600x600/prd-front-6283037-1-600x600.jpg"
}