{
  "type": "product",
  "currency": "EUR",
  "itemName": "True Spirit Telefoontasje",
  "code": "6412894",
  "price": "6.99",
  "priceOriginal": "",
  "itemBgbcat": "2048 > 2244 > 2578 > 3199 > 4869 > 6412",
  "supplier": "MIJNSCHOENENSHOP.NL",
  "inStock": "inStock",
  "onPromo": "1062792",
  "mmkId": "1062792",
  "productGroupId": "531129",
  "brandType": "Eigen merk",
  "discount": "",
  "url": "/true-spirit-telefoontasje/p/6412894",
  "listName": "Lister",
  "brand": "Truespirit",
  "mpOrigin": "Kruidvat",
  "mpShopId": "1",
  "isSponsored": "false",
  "categories": [
    {
      "id": 29536082,
      "name": "Fashion"
    },
    {
      "id": 30266046,
      "name": "Accessoires"
    },
    {
      "id": 30266863,
      "name": "Tassen"
    },
    {
      "id": 101713689,
      "name": "Telefoontas"
    }
  ],
  "description": "roze, 20cm x 14cm",
  "image": "/medias/sys_master/prd-images/hbd/hfc/44682189996062/prd-front-6412894-1_600x600/prd-front-6412894-1-600x600.jpg"
}