{
  "type": "product",
  "currency": "EUR",
  "itemName": "True Spirit Luiertas",
  "code": "6259860",
  "price": "12.99",
  "priceOriginal": "",
  "itemBgbcat": "2048 > 2244 > 2578 > 3199 > 4869 > 6414",
  "supplier": "TRENDSOURCE BV",
  "inStock": "outOfStock",
  "onPromo": "",
  "mmkId": "",
  "productGroupId": "",
  "brandType": "Eigen merk",
  "discount": "",
  "url": "/true-spirit-luiertas/p/6259860",
  "listName": "Lister",
  "brand": "Truespirit",
  "mpOrigin": "Kruidvat",
  "mpShopId": "1",
  "isSponsored": "false",
  "categories": [
    {
      "id": 29536082,
      "name": "Fashion"
    },
    {
      "id": 30266046,
      "name": "Accessoires"
    },
    {
      "id": 30266863,
      "name": "Tassen"
    }
  ],
  "description": "zwart, 41cm x 21cm x 39cm",
  "image": "/medias/sys_master/prd-images/h63/ha2/33746397298718/prd-front-6259860-1_600x600/prd-front-6259860-1-600x600.jpg"
}