{
  "type": "product",
  "currency": "EUR",
  "itemName": "Villa Volance Faux Fur Dekbedovertrek",
  "code": "6336839",
  "price": "7.49",
  "priceOriginal": "14.99",
  "itemBgbcat": "2196 > 2453 > 2738 > 3440 > 5926 > 6020",
  "supplier": "VESPO BV",
  "inStock": "inStock",
  "onPromo": "1059368",
  "mmkId": "1059368",
  "productGroupId": "",
  "brandType": "Eigen merk",
  "discount": "€ 7,50",
  "url": "/villa-volance-faux-fur-dekbedovertrek/p/6336839",
  "listName": "Lister",
  "brand": "Villa Volance",
  "mpOrigin": "Kruidvat",
  "mpShopId": "1",
  "isSponsored": "false",
  "categories": [
    {
      "id": 30266078,
      "name": "Wonen"
    },
    {
      "id": 57225448,
      "name": "Slapen"
    },
    {
      "id": 65815325,
      "name": "Dekbedovertrekken"
    }
  ],
  "description": "beige, 140cm x 200cm",
  "image": "/medias/sys_master/prd-images/h1e/h58/35130939637790/prd-front-6336839-1_600x600/prd-front-6336839-1-600x600.jpg"
}