{
  "type": "product",
  "currency": "EUR",
  "itemName": "Cetaphil Optimal Hydration Revitaliserende Dagcrème",
  "code": "5888363",
  "price": "22.95",
  "priceOriginal": "",
  "itemBgbcat": "2002 > 2089 > 2256 > 2424 > 2832 > 3574",
  "supplier": "GALDERMA BENELUX BV",
  "inStock": "inStock",
  "onPromo": "1052196",
  "mmkId": "1052196",
  "productGroupId": "476482",
  "brandType": "A of B merk",
  "discount": "",
  "url": "/cetaphil-optimal-hydration-revitaliserende-dagcreme/p/5888363",
  "listName": "Lister",
  "brand": "Cetaphil",
  "mpOrigin": "Kruidvat",
  "mpShopId": "1",
  "isSponsored": "false",
  "categories": [
    {
      "id": 29536077,
      "name": "Beauty"
    },
    {
      "id": 30266606,
      "name": "Dermacare"
    }
  ],
  "description": "48g"
}