{
  "type": "product",
  "currency": "USD",
  "itemName": "Goliath Het Uilenbos",
  "code": "5918939",
  "price": "9.99",
  "priceOriginal": "",
  "itemBgbcat": "2181 > 5921 > 6018 > 6741 > 6740 > 6739",
  "supplier": "GOLIATH B.V.",
  "inStock": "inStock",
  "onPromo": "",
  "mmkId": "",
  "productGroupId": "",
  "brandType": "A of B merk",
  "discount": "",
  "url": "/goliath-het-uilenbos/p/5918939",
  "listName": "Lister",
  "brand": "Goliath",
  "mpOrigin": "Kruidvat",
  "mpShopId": "1",
  "isSponsored": "false",
  "categories": [
    {
      "id": 29536081,
      "name": "Speelgoed"
    },
    {
      "id": 30266027,
      "name": "Spellen en puzzels"
    },
    {
      "id": 30266835,
      "name": "Bordspellen"
    }
  ],
  "description": "Nederlandstalig spel",
  "image": "/medias/sys_master/prd-images/h14/h30/30112322289694/prd-front-5918939-1_600x600/prd-front-5918939-1-600x600.jpg"
}