{
  "type": "product",
  "currency": "EUR",
  "itemName": "NYX Professional Makeup Make 'Em Wonder 02 Fair Porcelain Foundation",
  "code": "6427685",
  "price": "14.99",
  "priceOriginal": "",
  "itemBgbcat": "2002 > 2069 > 2210 > 2378 > 2819 > 3560",
  "supplier": "NYX PROFESSIONAL MAKE-UP",
  "inStock": "outOfStock",
  "onPromo": "1060073",
  "mmkId": "1060073",
  "productGroupId": "513873",
  "brandType": "A of B merk",
  "discount": "",
  "url": "/nyx-professional-makeup-make-em-wonder-02-fair-porcelain-foundation/p/6427685",
  "listName": "Lister",
  "brand": "NYX Professional Makeup",
  "mpOrigin": "Kruidvat",
  "mpShopId": "1",
  "isSponsored": "false",
  "categories": [
    {
      "id": 29536077,
      "name": "Beauty"
    },
    {
      "id": 30265987,
      "name": "Make-up"
    },
    {
      "id": 30266577,
      "name": "Foundation"
    }
  ],
  "description": "",
  "image": "/medias/sys_master/prd-images/hdd/h90/46310672072734/temp-prd-front-6427685-1_600x600/temp-prd-front-6427685-1-600x600.jpg"
}