{
  "type": "product",
  "currency": "EUR",
  "itemName": "Gillette Intimate i5 Trimmer",
  "code": "5913227",
  "price": "69.99",
  "priceOriginal": "",
  "itemBgbcat": "2003 > 2088 > 2255 > 6672 > 5887 > 6445",
  "supplier": "PROCTER & GAMBLE NL BV",
  "inStock": "inStock",
  "onPromo": "1055475",
  "mmkId": "1055475",
  "productGroupId": "498962",
  "brandType": "A of B merk",
  "discount": "",
  "url": "/gillette-intimate-i5-trimmer/p/5913227",
  "listName": "Lister",
  "brand": "Gillette",
  "mpOrigin": "Kruidvat",
  "mpShopId": "1",
  "isSponsored": "false",
  "categories": [
    {
      "id": 29536078,
      "name": "Verzorging"
    },
    {
      "id": 30266002,
      "name": "Scheren en ontharen"
    },
    {
      "id": 30266684,
      "name": "Multigroomers"
    }
  ],
  "description": "Inclusief 3 opzetstukken",
  "image": "/medias/sys_master/prd-images/h63/hc6/28370922536990/prd-front-5913227-1_600x600/prd-front-5913227-1-600x600.jpg"
}