{
  "type": "product",
  "currency": "EUR",
  "itemName": "Kruidvat Cotton Stretch Damesslip",
  "code": "6326822",
  "price": "2.99",
  "priceOriginal": "5.99",
  "itemBgbcat": "2001 > 2095 > 2150 > 2644 > 6616 > 6617",
  "supplier": "BECONNECTED HK LTD",
  "inStock": "outOfStock",
  "onPromo": "1059284",
  "mmkId": "1059284",
  "productGroupId": "514141",
  "brandType": "Eigen merk",
  "discount": "€ 3,00",
  "url": "/kruidvat-cotton-stretch-damesslip/p/6326822",
  "listName": "Lister",
  "brand": "Kruidvat",
  "mpOrigin": "Kruidvat",
  "mpShopId": "1",
  "isSponsored": "false",
  "categories": [
    {
      "id": 29536082,
      "name": "Fashion"
    },
    {
      "id": 30266039,
      "name": "Dames"
    },
    {
      "id": 30266842,
      "name": "Damesondergoed"
    }
  ],
  "description": "zwart, mt M, 2 stuks",
  "image": "/medias/sys_master/prd-images/h3f/haf/44390539427870/prd-front-6326822-1_600x600/prd-front-6326822-1-600x600.jpg"
}