{
  "type": "product",
  "currency": "EUR",
  "itemName": "Clementoni La Casa de Papel Puzzel",
  "code": "6305493",
  "price": "4.99",
  "priceOriginal": "",
  "itemBgbcat": "2181 > 5166 > 5237 > 5426 > 5921 > 6018",
  "supplier": "HERMANEX INTERNATIONAL",
  "inStock": "inStock",
  "onPromo": "1053594",
  "mmkId": "1053594",
  "productGroupId": "487731",
  "brandType": "Ander merk",
  "discount": "",
  "url": "/clementoni-la-casa-de-papel-puzzel/p/6305493",
  "listName": "Lister",
  "brand": "Clementoni",
  "mpOrigin": "Kruidvat",
  "mpShopId": "1",
  "isSponsored": "false",
  "categories": [
    {
      "id": 29536081,
      "name": "Speelgoed"
    },
    {
      "id": 90170187,
      "name": "Puzzels"
    }
  ],
  "description": "1000 stukjes",
  "image": "/medias/sys_master/prd-images/hf6/ha0/34436524867614/prd-front-6305493-1_600x600/prd-front-6305493-1-600x600.jpg"
}