{
  "type": "product",
  "currency": "EUR",
  "itemName": "Catrice AirBlush Matt 150 Wine Time Blush",
  "code": "6233666",
  "price": "4.49",
  "priceOriginal": "",
  "itemBgbcat": "2002 > 2069 > 2210 > 2378 > 2819 > 5687",
  "supplier": "COSNOVA GMBH (BNL)",
  "inStock": "inStock",
  "onPromo": "1058548",
  "mmkId": "1058548",
  "productGroupId": "524247",
  "brandType": "Exclusief merk",
  "discount": "",
  "url": "/catrice-airblush-matt-150-wine-time-blush/p/6233666",
  "listName": "Lister",
  "brand": "Catrice",
  "mpOrigin": "Kruidvat",
  "mpShopId": "1",
  "isSponsored": "false",
  "categories": [
    {
      "id": 29536077,
      "name": "Beauty"
    },
    {
      "id": 30265987,
      "name": "Make-up"
    },
    {
      "id": 30266590,
      "name": "Blush"
    }
  ],
  "description": "5,5g"
}