{
  "type": "product",
  "currency": "EUR",
  "itemName": "Philips Sonicare S2 Sensitive Hx6052/87 Opzetborstels",
  "code": "6036322",
  "price": "19.99",
  "priceOriginal": "",
  "itemBgbcat": "2003 > 2075 > 2223 > 2885 > 4228 > 5693",
  "supplier": "PHILIPS CONSUMER LIFESTYLE BV",
  "inStock": "inStock",
  "onPromo": "1051820",
  "mmkId": "1051820",
  "productGroupId": "478550",
  "brandType": "A of B merk",
  "discount": "",
  "url": "/philips-sonicare-s2-sensitive-hx6052/87-opzetborstels/p/6036322",
  "listName": "Lister",
  "brand": "Philips",
  "mpOrigin": "Kruidvat",
  "mpShopId": "1",
  "isSponsored": "false",
  "categories": [
    {
      "id": 29536078,
      "name": "Verzorging"
    },
    {
      "id": 30266001,
      "name": "Mondverzorging"
    },
    {
      "id": 30266675,
      "name": "Opzetborstels"
    }
  ],
  "description": "wit, 2 stuks",
  "image": "/medias/sys_master/prd-images/h39/h2f/32897032585246/prd-front-6036322-1_600x600/prd-front-6036322-1-600x600.jpg"
}