{
  "type": "product",
  "currency": "USD",
  "itemName": "Braun Series 9 Pro+ 9515s Elektrisch Scheerapparaat",
  "code": "6197980",
  "price": "210.0",
  "priceOriginal": "419.99",
  "itemBgbcat": "2003 > 2088 > 2255 > 6441 > 6672 > 6673",
  "supplier": "PROCTER & GAMBLE NL BV",
  "inStock": "outOfStock",
  "onPromo": "1059368",
  "mmkId": "1059368",
  "productGroupId": "",
  "brandType": "A of B merk",
  "discount": "$ 209,99",
  "url": "/braun-series-9-pro-9515s-elektrisch-scheerapparaat/p/6197980",
  "listName": "Lister",
  "brand": "Braun",
  "mpOrigin": "Kruidvat",
  "mpShopId": "1",
  "isSponsored": "false",
  "categories": [
    {
      "id": 29536078,
      "name": "Verzorging"
    },
    {
      "id": 30266002,
      "name": "Scheren en ontharen"
    },
    {
      "id": 30266680,
      "name": "Elektrische scheerapparaten"
    }
  ],
  "description": "grafiet",
  "image": "/medias/sys_master/prd-images/h11/h29/34028440748062/prd-front-6197980-1_600x600/prd-front-6197980-1-600x600.jpg"
}