{
  "type": "product",
  "currency": "EUR",
  "itemName": "Kruidvat Terry Slabbetjes",
  "code": "6426719",
  "price": "3.99",
  "priceOriginal": "",
  "itemBgbcat": "2001 > 2033 > 2128 > 2313 > 2709 > 3412",
  "supplier": "MUNDIA BV",
  "inStock": "outOfStock",
  "onPromo": "1010662",
  "mmkId": "1010662",
  "productGroupId": "242521",
  "brandType": "Eigen merk",
  "discount": "",
  "url": "/kruidvat-terry-slabbetjes/p/6426719",
  "listName": "Lister",
  "brand": "Kruidvat",
  "mpOrigin": "Kruidvat",
  "mpShopId": "1",
  "isSponsored": "false",
  "categories": [
    {
      "id": 29536080,
      "name": "Baby"
    },
    {
      "id": 30266022,
      "name": "Babyvoedingsaccessoires"
    },
    {
      "id": 30266802,
      "name": "Slabbetjes"
    }
  ],
  "description": "2 stuks"
}