{
  "type": "product",
  "currency": "EUR",
  "itemName": "NYX Professional Makeup 3 Vivid Rich Tigers Prize Mechanical Liner",
  "code": "6130115",
  "price": "7.95",
  "priceOriginal": "",
  "itemBgbcat": "2002 > 2069 > 2210 > 2422 > 2894 > 3669",
  "supplier": "NYX PROFESSIONAL MAKE-UP",
  "inStock": "inStock",
  "onPromo": "1051400",
  "mmkId": "1051400",
  "productGroupId": "470499",
  "brandType": "A of B merk",
  "discount": "",
  "url": "/nyx-professional-makeup-3-vivid-rich-tigers-prize-mechanical-liner/p/6130115",
  "listName": "Lister",
  "brand": "NYX Professional Makeup",
  "mpOrigin": "Kruidvat",
  "mpShopId": "1",
  "isSponsored": "false",
  "categories": [
    {
      "id": 29536077,
      "name": "Beauty"
    },
    {
      "id": 30265987,
      "name": "Make-up"
    },
    {
      "id": 30266585,
      "name": "Oogpotlood"
    }
  ],
  "description": "",
  "image": "/medias/sys_master/prd-images/h2a/h21/31926141419550/prd-front-6130115-1_600x600/prd-front-6130115-1-600x600.jpg"
}