{
  "type": "product",
  "currency": "EUR",
  "itemName": "Bausch & Lomb -2.50 Maandlenzen",
  "code": "6131907",
  "price": "22.99",
  "priceOriginal": "",
  "itemBgbcat": "2006 > 2074 > 2155 > 3027 > 6779 > 6785",
  "supplier": "OTC MEDICAL BV",
  "inStock": "inStock",
  "onPromo": "1059708",
  "mmkId": "1059708",
  "productGroupId": "516434",
  "brandType": "A of B merk",
  "discount": "",
  "url": "/bausch-lomb-250-maandlenzen/p/6131907",
  "listName": "Lister",
  "brand": "Bausch & Lomb",
  "mpOrigin": "Kruidvat",
  "mpShopId": "1",
  "isSponsored": "false",
  "categories": [
    {
      "id": 29536079,
      "name": "Gezondheid"
    },
    {
      "id": 30266013,
      "name": "Optiek"
    },
    {
      "id": 30266758,
      "name": "Lenzen"
    },
    {
      "id": 30266997,
      "name": "Maandlenzen"
    }
  ],
  "description": "Medisch hulpmiddel - 6 stuks",
  "image": "/medias/sys_master/prd-images/h5f/he8/31943163314206/prd-front-6131907-1_600x600/prd-front-6131907-1-600x600.jpg"
}