{
  "type": "product",
  "currency": "EUR",
  "itemName": "Depend Orange Sticks",
  "code": "6312801",
  "price": "1.99",
  "priceOriginal": "",
  "itemBgbcat": "2002 > 6497 > 6496 > 6505 > 6506 > 6520",
  "supplier": "LEIJTENS IMPORT BV",
  "inStock": "inStock",
  "onPromo": "",
  "mmkId": "",
  "productGroupId": "",
  "brandType": "Exclusief merk",
  "discount": "",
  "url": "/depend-orange-sticks/p/6312801",
  "listName": "Lister",
  "brand": "Depend Gel iQ",
  "mpOrigin": "Kruidvat",
  "mpShopId": "1",
  "isSponsored": "false",
  "categories": [
    {
      "id": 29536077,
      "name": "Beauty"
    },
    {
      "id": 72475724,
      "name": "Nagels"
    },
    {
      "id": 30265994,
      "name": "Nagelverzorging"
    },
    {
      "id": 30266632,
      "name": "Nagelaccessoires"
    },
    {
      "id": 87391028,
      "name": "Nepnageltools"
    }
  ],
  "description": "3 stuks",
  "image": "/medias/sys_master/prd-images/h46/h49/35174911705118/prd-front-6312801-1_600x600/prd-front-6312801-1-600x600.jpg"
}