{
  "type": "product",
  "currency": "EUR",
  "itemName": "Twinkle Pets Kralenset",
  "code": "6413580",
  "price": "8.99",
  "priceOriginal": "",
  "itemBgbcat": "5921 > 6040 > 2232 > 5177 > 5271 > 5460",
  "supplier": "UP INTERNATIONAL BV",
  "inStock": "inStock",
  "onPromo": "",
  "mmkId": "",
  "productGroupId": "",
  "brandType": "Ander merk",
  "discount": "",
  "url": "/twinkle-pets-kralenset/p/6413580",
  "listName": "Lister",
  "brand": "Overig",
  "mpOrigin": "Kruidvat",
  "mpShopId": "1",
  "isSponsored": "false",
  "categories": [
    {
      "id": 29536081,
      "name": "Speelgoed"
    },
    {
      "id": 30266030,
      "name": "Knutselen"
    }
  ],
  "description": ""
}