{
  "type": "product",
  "currency": "EUR",
  "itemName": "Kruidvat Matrasbeschermer",
  "code": "6284185",
  "price": "9.49",
  "priceOriginal": "",
  "itemBgbcat": "2001 > 2130 > 2317 > 2718 > 3421 > 4362",
  "supplier": "MUNDIA BV",
  "inStock": "inStock",
  "onPromo": "1052997",
  "mmkId": "1052997",
  "productGroupId": "483678",
  "brandType": "Eigen merk",
  "discount": "",
  "url": "/kruidvat-matrasbeschermer/p/6284185",
  "listName": "Lister",
  "brand": "Kruidvat",
  "mpOrigin": "Kruidvat",
  "mpShopId": "1",
  "isSponsored": "false",
  "categories": [
    {
      "id": 29536080,
      "name": "Baby"
    },
    {
      "id": 49880164,
      "name": "Babykamer"
    },
    {
      "id": 51606844,
      "name": "Baby beddengoed"
    },
    {
      "id": 64170341,
      "name": "Babymatrasbeschermers"
    }
  ],
  "description": "wit, 60cm x 120cm"
}