{
  "type": "product",
  "currency": "EUR",
  "itemName": "Walibi Holland 12+ Jaar Ticket",
  "code": "4771348",
  "price": "30.0",
  "priceOriginal": "44.5",
  "itemBgbcat": "4870 > 6447 > 4891 > 6540 > 6541 > 6542",
  "supplier": "WALIBI HOLLAND BV",
  "inStock": "inStock",
  "onPromo": "",
  "mmkId": "",
  "productGroupId": "",
  "brandType": "Ander merk",
  "discount": "€ 14,50",
  "url": "/walibi-holland-12-jaar-ticket/p/4771348",
  "listName": "Lister",
  "brand": "Overig",
  "mpOrigin": "Kruidvat",
  "mpShopId": "1",
  "isSponsored": "false",
  "categories": [
    {
      "id": 29536083,
      "name": "Tickets"
    },
    {
      "id": 30266047,
      "name": "Dagje uit"
    },
    {
      "id": 30266869,
      "name": "Pretpark"
    }
  ],
  "description": "Verzilver je unieke code via de link in de productinformatie"
}