{
  "type": "product",
  "currency": "EUR",
  "itemName": "Curanol Tabletten",
  "code": "3758651",
  "price": "6.99",
  "priceOriginal": "",
  "itemBgbcat": "2006 > 2087 > 2123 > 2500 > 3102 > 3965",
  "supplier": "NIA CARE BV",
  "inStock": "inStock",
  "onPromo": "1053369",
  "mmkId": "1053369",
  "productGroupId": "459732",
  "brandType": "A of B merk",
  "discount": "",
  "url": "/curanol-tabletten/p/3758651",
  "listName": "Lister",
  "brand": "Curanol",
  "mpOrigin": "Kruidvat",
  "mpShopId": "1",
  "isSponsored": "false",
  "categories": [
    {
      "id": 29536079,
      "name": "Gezondheid"
    },
    {
      "id": 30266006,
      "name": "Zelfzorg"
    },
    {
      "id": 30266702,
      "name": "Intieme ongemakken"
    },
    {
      "id": 49949753,
      "name": "Anale verzorging"
    }
  ],
  "description": "40 stuks",
  "image": "/medias/sys_master/prd-images/h3b/h60/29034646044702/prd-front-3758651-1_600x600/prd-front-3758651-1-600x600.jpg"
}