{
  "type": "product",
  "currency": "EUR",
  "itemName": "L'Oréal Paris Revitalift Vitamin C Pore Perfecting Toner",
  "code": "6237243",
  "price": "22.99",
  "priceOriginal": "",
  "itemBgbcat": "2002 > 2089 > 2256 > 2804 > 4226 > 6702",
  "supplier": "LOREAL NED BV",
  "inStock": "inStock",
  "onPromo": "1054500",
  "mmkId": "1054500",
  "productGroupId": "469003",
  "brandType": "A of B merk",
  "discount": "",
  "url": "/loreal-paris-revitalift-vitamin-c-pore-perfecting-toner/p/6237243",
  "listName": "Lister",
  "brand": "L'Oreal Paris",
  "mpOrigin": "Kruidvat",
  "mpShopId": "1",
  "isSponsored": "false",
  "categories": [
    {
      "id": 29536077,
      "name": "Beauty"
    },
    {
      "id": 30265991,
      "name": "Skincare"
    },
    {
      "id": 30266608,
      "name": "Gezichtsreiniging"
    },
    {
      "id": 73443559,
      "name": "Toner"
    }
  ],
  "description": "180ml",
  "image": "/medias/sys_master/prd-images/hd4/h82/33351084408862/prd-front-6237243-1_600x600/prd-front-6237243-1-600x600.jpg"
}